{
  "version": 1,
  "events": [
    {
      "at": "2026-07-23T22:24:25-03:00",
      "event": "transition",
      "from": "001_initial_task",
      "to": "002_planning",
      "contexts": [],
      "test_seconds": 0,
      "result": "advanced"
    },
    {
      "at": "2026-07-23T22:30:49-03:00",
      "event": "transition",
      "from": "002_planning",
      "to": "003_human_approval",
      "contexts": [
        "plan_6_1_1"
      ],
      "test_seconds": 0,
      "result": "advanced"
    },
    {
      "at": "2026-07-23T22:38:00-03:00",
      "event": "stage",
      "stage": "003_human_approval",
      "contexts": [
        "critic_003_6_1_1"
      ],
      "returns": 0,
      "strategy": "strong independent adversarial plan review",
      "tests": "card, plan, and linked durable specs inspected",
      "test_seconds": 0,
      "result": "approved"
    },
    {
      "at": "2026-07-23T22:34:36-03:00",
      "event": "transition",
      "from": "003_human_approval",
      "to": "004_processing",
      "contexts": [
        "critic_003_6_1_1"
      ],
      "test_seconds": 0,
      "result": "advanced"
    },
    {
      "at": "2026-07-23T22:38:42-03:00",
      "event": "transition",
      "from": "004_processing",
      "to": "005_verifying",
      "contexts": [
        "exec_6_1_1"
      ],
      "test_seconds": 0,
      "result": "advanced"
    },
    {
      "at": "2026-07-23T22:47:13-03:00",
      "event": "stage",
      "stage": "005_verifying",
      "contexts": [
        "critic_005_6_1_1"
      ],
      "returns": 1,
      "strategy": "full critical review of original request, contracts, route inventory, diff, DOX, and baseline-classified gates",
      "tests": "pop_validate pass; diff/scope/rg pass; lint pass; build pass; check/typecheck and test retain documented unchanged baseline failures",
      "test_seconds": 27,
      "result": "returned"
    },
    {
      "at": "2026-07-23T22:49:34-03:00",
      "event": "transition",
      "from": "005_verifying",
      "to": "004_processing",
      "contexts": [
        "verify_6_1_1"
      ],
      "test_seconds": 27.0,
      "result": "returned"
    },
    {
      "at": "2026-07-23T22:56:12-03:00",
      "event": "transition",
      "from": "004_processing",
      "to": "005_verifying",
      "contexts": [
        "exec_6_1_1"
      ],
      "test_seconds": 0,
      "result": "advanced"
    },
    {
      "at": "2026-07-23T22:59:55-03:00",
      "event": "stage",
      "stage": "005_verifying",
      "contexts": [
        "critic_005_round2_6_1_1"
      ],
      "returns": 2,
      "strategy": "full critical round-2 review of original request, both prior blockers, contracts, route/auth inventory, complete diff, DOX, scope, and baseline-classified gates",
      "tests": "pop_validate pass; diff/scope/acceptance probes pass; lint pass; check/typecheck and test retain documented unchanged baseline failures; prior build evidence audited for documentation-only repair",
      "test_seconds": 15,
      "result": "returned"
    },
    {
      "at": "2026-07-23T23:00:55-03:00",
      "event": "transition",
      "from": "005_verifying",
      "to": "004_processing",
      "contexts": [
        "verify2_6_1_1"
      ],
      "test_seconds": 15.0,
      "result": "returned"
    },
    {
      "at": "2026-07-23T23:02:46-03:00",
      "event": "transition",
      "from": "004_processing",
      "to": "005_verifying",
      "contexts": [
        "exec_6_1_1"
      ],
      "test_seconds": 0,
      "result": "advanced"
    },
    {
      "at": "2026-07-23T23:06:23-03:00",
      "event": "stage",
      "stage": "005_verifying",
      "contexts": [
        "critic_005_round3_6_1_1"
      ],
      "returns": 2,
      "strategy": "full critical round-3 review of original request, all prior blockers, contracts, route/auth inventory, complete diff, DOX, scope, and baseline-classified gates",
      "tests": "pop_validate, diff/scope/acceptance probes, focused authorization tests, lint, and build pass; check/typecheck and full test retain documented unchanged baseline failures",
      "test_seconds": 25,
      "result": "approved"
    },
    {
      "at": "2026-07-23T23:07:55-03:00",
      "event": "transition",
      "from": "005_verifying",
      "to": "006_done",
      "contexts": [
        "verify3_6_1_1"
      ],
      "test_seconds": 15.0,
      "result": "advanced"
    }
  ]
}
